pyAn/__init__.py
pyAn-0.1.3.dist-info/LICENSE
pyAn-0.1.3.dist-info/METADATA
pyAn-0.1.3.dist-info/WHEEL
pyAn-0.1.3.dist-info/top_level.txt
pyAn-0.1.3.dist-info/RECORD
