Metadata-Version: 2.1
Name: pyAn
Version: 0.1.3
Summary: Animation with turtle.
Home-page: https://repl.it/@DatM314/pyAnimate
Author: DatM314
Author-email: program.bat6@gmail.com
License: UNKNOWN
Platform: UNKNOWN
Classifier: Programming Language :: Python :: 3
Classifier: License :: OSI Approved :: MIT License
Classifier: Operating System :: OS Independent
Requires-Python: >=3.6
